dsmga2-0.2.0.dist-info/METADATA
dsmga2-0.2.0.dist-info/WHEEL
dsmga2/__init__.py
dsmga2/_dsmga2.cpython-314-darwin.so
dsmga2/py.typed
dsmga2-0.2.0.dist-info/RECORD
