Metadata-Version: 2.4
Name: dsmga2
Version: 0.2.0
Classifier: Development Status :: 4 - Beta
Classifier: Intended Audience :: Science/Research
Classifier: Intended Audience :: Developers
Classifier: License :: OSI Approved :: MIT License
Classifier: License :: OSI Approved :: Apache Software License
Classifier: Programming Language :: Python :: 3
Classifier: Programming Language :: Python :: 3.8
Classifier: Programming Language :: Python :: 3.9
Classifier: Programming Language :: Python :: 3.10
Classifier: Programming Language :: Python :: 3.11
Classifier: Programming Language :: Python :: 3.12
Classifier: Programming Language :: Rust
Classifier: Topic :: Scientific/Engineering :: Artificial Intelligence
Summary: Dependency Structure Matrix Genetic Algorithm II - A fast genetic algorithm with linkage learning
Keywords: genetic-algorithm,optimization,evolutionary-computation,linkage-learning
Home-Page: https://github.com/PoHsuanLai/dsmga2
Author: Po-Hsuan Lai
License: MIT OR Apache-2.0
Requires-Python: >=3.8
